{"name":"Reservar hotel","id":"ct05---reservar-hotel-1-estrela-são-paulo:Reservar hotel","testSteps":[{"number":1,"description":"Given estou na pagina do site do hotel urbano \"\u003curl\u003e\"","duration":22490,"startTime":1517502753469,"screenshots":[{"screenshot":"65bae06258817f0e0f52cf06acb857ce9c5ab3cd0a9433c68d7086bd771e5199.png"}],"result":"SUCCESS","precondition":false,"children":[{"number":2,"description":"Abrir pagina: https://www.hotelurbano.com/","duration":21745,"startTime":1517502753500,"screenshots":[{"screenshot":"108f248a1e266c572efe37cea942cf1cffce42304d1b5207e527396f566a803f.png"}],"result":"SUCCESS","precondition":false}]},{"number":3,"description":"When clico no menu \u0027Hoteis\u0027 na barra superior","duration":14172,"startTime":1517502775960,"screenshots":[{"screenshot":"224e4355b1e9722f25e1d7587931eb580bcafc51b17796f10987f9995be835af.png"}],"result":"SUCCESS","precondition":false},{"number":4,"description":"And preencho o campo de \u0027Pesquisa\u0027 \"\u003cpesquisa\u003e\"","duration":1753,"startTime":1517502790133,"screenshots":[{"screenshot":"58ab3d4657f82bd7545e94851c31518a41479892c9a0b201bb8a48454a38fa42.png"},{"screenshot":"13b6cba319fbcf795f4eab867ef95f695bd8b11158a7eb8a29ab267fbd4ebcb5.png"}],"result":"SUCCESS","precondition":false},{"number":5,"description":"And clico no botao \u0027Buscar\u0027","duration":13264,"startTime":1517502791886,"screenshots":[{"screenshot":"153959b35fe04a7a5d225733e74fdd82941e38f256c85392c231c42d809b8d6e.png"},{"screenshot":"670c280e86bf21a49d1267a8f32cbe677c3391385eb76b72337808909e6ef93a.png"}],"result":"SUCCESS","precondition":false},{"number":6,"description":"And seleciono o nivel de \u0027Categoria\u0027 \"\u003cqtdEstrelas\u003e\"","duration":3206,"startTime":1517502805151,"screenshots":[{"screenshot":"70bfaa0a3151d8f48c8edd9d69151748f468a1c02295af9f838cf8084e89ef3c.png"},{"screenshot":"dc77f60f2a73028c0a7f22e5053698ca3e5e9ec40c5f83ab78ed722b9e414a86.png"}],"result":"SUCCESS","precondition":false},{"number":7,"description":"And clico no link \u0027Ver\u0027 \"\u003cnomeHotel\u003e\"","duration":10537,"startTime":1517502808358,"screenshots":[{"screenshot":"d8cc02e77115ab627328d61fa71a52811573d52a6df665ead51f0bbfd82623e3.png"},{"screenshot":"2690be8f6d072716ffb200d41f52511821794c0591f4c9b59a9d3b6cc891a850.png"}],"result":"SUCCESS","precondition":false},{"number":8,"description":"And verifico o link do hotel clicado \"\u003cqtdEstrelas\u003e\"","duration":1016,"startTime":1517502818895,"screenshots":[{"screenshot":"2690be8f6d072716ffb200d41f52511821794c0591f4c9b59a9d3b6cc891a850.png"}],"result":"SUCCESS","precondition":false},{"number":9,"description":"And preencho o campo \u0027Entrada\u0027 \"\u003cdataEntrada\u003e\"","duration":5105,"startTime":1517502819911,"screenshots":[{"screenshot":"dda44e822a3db4a97549bb82236cf586da55da32b57f564493b6afd0742c6804.png"}],"result":"SUCCESS","precondition":false},{"number":10,"description":"And preencho o campo \u0027Saida\u0027 \"\u003cdataSaida\u003e\"","duration":8256,"startTime":1517502825017,"screenshots":[{"screenshot":"ccfda401ef849783ad6bf33a86ff3872783ccab46ba3a7d9e95f48302c16cc04.png"}],"result":"SUCCESS","precondition":false},{"number":11,"description":"And seleciono a ddl \u0027Quartos\u0027 \"\u003cqtdQuartos\u003e\"","duration":1328,"startTime":1517502833274,"screenshots":[{"screenshot":"e6659c0eb1d105cd0c8e08dc88018f61760d01dc9ed662ebdcbabce81101d248.png"},{"screenshot":"79e6ae15097061fb73d877f52e860b0bf08a6de122d80655947e5804e4651c2a.png"}],"result":"SUCCESS","precondition":false},{"number":12,"description":"And seleciono a ddl \u0027Adultos\u0027 \"\u003cqtdAdultos\u003e\"","duration":1279,"startTime":1517502834603,"screenshots":[{"screenshot":"04a7f110af61379ce8dbf56f352a48df76ed6fb9e0ee9522f8825ffb410fa33e.png"}],"result":"SUCCESS","precondition":false},{"number":13,"description":"And seleciono a ddl \u0027Criancas\u0027 \"\u003cqtdCriancas\u003e\"","duration":1136,"startTime":1517502835883,"screenshots":[{"screenshot":"04a7f110af61379ce8dbf56f352a48df76ed6fb9e0ee9522f8825ffb410fa33e.png"}],"result":"SUCCESS","precondition":false},{"number":14,"description":"And clicar botao \u0027Verificar Disponibilidade\u0027","duration":1205,"startTime":1517502837020,"screenshots":[{"screenshot":"415273247946eef50abce539d2698f22e8db8c70504fc55cdd039ed83f0c97ae.png"}],"result":"SUCCESS","precondition":false},{"number":15,"description":"And seleciono a ddl \u0027Numero de Quartos\u0027 \"\u003cposDdl\u003e\" \"\u003cqtdQuartos\u003e\"","duration":1677,"startTime":1517502838227,"screenshots":[{"screenshot":"6d335a4715acf1f3dd25e5f5f681eb8495591967fefbcc2306352539d7d12964.png"},{"screenshot":"f24edf0651c989a6a521bb50d772371e05b8ca51c8a5a667c7f069fa11492919.png"}],"result":"SUCCESS","precondition":false},{"number":16,"description":"And clico no botao \u0027Reservar\u0027","duration":17180,"startTime":1517502839904,"screenshots":[{"screenshot":"d8f74d532a846429d8f5439624eab58ab9ef76f9deb792dbae2766e78bb1bb5e.png"},{"screenshot":"c90d557f83cd5e2ad5db41d8b63dcf95c8db5ad1367e8bfb035fa664fe0eee09.png"}],"result":"SUCCESS","precondition":false},{"number":17,"description":"And preencho o campo \u0027Email\u0027 \"\u003cemail\u003e\"","duration":1171,"startTime":1517502857084,"screenshots":[{"screenshot":"70c852a6b70cf36a2ac149c955b37080c3c47ae7ac16602424a5192a154c1407.png"}],"result":"SUCCESS","precondition":false},{"number":18,"description":"And preencher campos \u0027Responsavel do Quarto\u0027 \"\u003cqtdQuartos\u003e\" \"\u003cnomeResp\u003e\"","duration":1279,"startTime":1517502858255,"screenshots":[{"screenshot":"2ab8a169f3d5796bb991231b045dfa4ce86fb06f663f218881562ecc8a4cf8b5.png"},{"screenshot":"1b22058aa193ac71a8fb3b5f40578ae533e5951a23bbb6baeabf8369f91e1e23.png"}],"result":"SUCCESS","precondition":false},{"number":19,"description":"And preencho o campo \u0027Cpf\u0027 \"\u003ccpf\u003e\"","duration":988,"startTime":1517502859534,"screenshots":[{"screenshot":"632773107634308c8386a354b1c5209945be0cf8e043d294487ae9406de72bca.png"},{"screenshot":"7adf4c82a76211682fe5f390abf1ae3481779262c69a6c52df01be06ad95dbf5.png"}],"result":"SUCCESS","precondition":false},{"number":20,"description":"And preencho o campo \u0027Data de Nascimento\u0027 \"\u003cdtNasc\u003e\"","duration":904,"startTime":1517502860523,"screenshots":[{"screenshot":"836f7a11d0a22af2b613e93c1226a4bb7a55a5226ccc616b1f673300402ebc26.png"},{"screenshot":"7f82cb9187864f14d456d5156f3cefe35f607b9e0714f3eff1753365923a37c1.png"}],"result":"SUCCESS","precondition":false},{"number":21,"description":"And preencho o campo \u0027Telefone\u0027 \"\u003ctel\u003e\"","duration":900,"startTime":1517502861427,"screenshots":[{"screenshot":"69cbc1da0541a202ec808c74a0e3df71962531276fc5a7455503fb5cbcc06980.png"},{"screenshot":"fec4169177727a7acd10f6c064b19187fa2616aa27ec6dcdd4e0b966d4c53de4.png"}],"result":"SUCCESS","precondition":false},{"number":22,"description":"And preencho o campo \u0027Numero do Cartao\u0027 \"\u003cnumCartao\u003e\"","duration":958,"startTime":1517502862343,"screenshots":[{"screenshot":"e7289565ec0f422f54ed84cb7aac29feaca2ee903bf72b25a793f5bf752d3a0d.png"},{"screenshot":"2c562d3b7641058a58e3c338754c9f192ed1435a2a6afa8615af268e98674d3e.png"}],"result":"SUCCESS","precondition":false},{"number":23,"description":"And preencho o campo \u0027Titular\u0027 \"\u003ctitular\u003e\"","duration":2617,"startTime":1517502863301,"screenshots":[{"screenshot":"031122db8eef1305cac9597c640e354157cc7b00c1555cb40878d699382409fb.png"},{"screenshot":"e054daa6b8de0cef1df296873887fb2b8f19d01ce11708eedaa424cb23f84c54.png"}],"result":"SUCCESS","precondition":false},{"number":24,"description":"And preencho o campo \u0027Validade\u0027 \"\u003cvalidade\u003e\"","duration":867,"startTime":1517502865918,"screenshots":[{"screenshot":"268ca84134cb43a69cbd34a1605435f15497c505bc373c006b297e4435b115ba.png"},{"screenshot":"e23ed3f1e680ae7c1c7f9d693c3f2a6a7119ce5c934273f9e41450840d7f072d.png"}],"result":"SUCCESS","precondition":false},{"number":25,"description":"And preencho o campo \u0027Codigo de Seguranca\u0027 \"\u003ccodSeg\u003e\"","duration":816,"startTime":1517502866785,"screenshots":[{"screenshot":"a6f1dd04c3ec4b7355eec792f74e83a0589b5c85c74ecbed1722bbdc997c9324.png"}],"result":"SUCCESS","precondition":false},{"number":26,"description":"And seleciono o numero de \u0027Parcelas\u0027 \"\u003cqtdParcelas\u003e\"","duration":953,"startTime":1517502867601,"screenshots":[{"screenshot":"25f0e52613342c59d032956039755f353b6ca90547cbcd04f9587da3dbed1099.png"},{"screenshot":"269991e02c9b576dba474459f192fe3d73425300608822619bdc2637b1833916.png"}],"result":"SUCCESS","precondition":false},{"number":27,"description":"Then clico na ckb \u0027Armazenar dados\u0027 \"\u003carmazenarDados\u003e\"","duration":860,"startTime":1517502868554,"screenshots":[{"screenshot":"a698260bcd8ceca1c19cb687ffb48a7c827d2d2ade7e12816f834abd53bcb896.png"},{"screenshot":"ca349e8b0fbc21939ff0e6e6e97ca533c6791f8d4d99a5d786a93231b2a05d68.png"}],"result":"SUCCESS","precondition":false}],"userStory":{"id":"ct05---reservar-hotel-1-estrela-são-paulo","storyName":"CT05 - Reservar hotel 1 estrela São Paulo","path":"CT05_ReservarHotelSaoPaulo1Estrela.feature","type":"feature"},"featureTag":{"name":"CT05 - Reservar hotel 1 estrela São Paulo","type":"feature"},"title":"Reservar hotel","description":"","tags":[{"name":"CT05 - Reservar hotel 1 estrela São Paulo","type":"feature"},{"name":"reservaHotel","type":"tag"}],"startTime":1517502753469,"duration":0,"projectKey":"","dataTable":{"headers":["url","pesquisa","qtdEstrelas","nomeHotel","dataEntrada","dataSaida","qtdQuartos","qtdAdultos","qtdCriancas","posDdl","nomeResp","email","cpf","dtNasc","tel","numCartao","titular","validade","codSeg","qtdParcelas","armazenarDados"],"rows":[{"values":["https://www.hotelurbano.com/","São Paulo","1","Balcony Hostel e Hotel","13/03/2018","27/07/2018","2","1","0","1","Sr. Responsavel","usuario@email.com","18277552530","02/02/2000","11999999999","4556905972222574","Usuario de Testes","10/19","300","4","true"],"result":"SUCCESS"}],"predefinedRows":true,"dataSetDescriptors":[{"startRow":0,"rowCount":0,"name":"","description":""}]},"manual":false,"result":"SUCCESS"}